wands/__init__.py
wands/__version__.py
wands/cmd.py
wands/main.py
wands/data/__init__.py
wands/data/area_base.csv
wands/data/load_data.py
wands/parse/__init__.py
wands/parse/address_parse.py
wands/script/__init__.py
wands/script/spider.py
wands/server/__init__.py
wands/server/manage.py
wands/server/views/__init__.py
wands/server/views/search.py
wands_ce-1.0.4.dist-info/LICENSE
wands_ce-1.0.4.dist-info/METADATA
wands_ce-1.0.4.dist-info/WHEEL
wands_ce-1.0.4.dist-info/entry_points.txt
wands_ce-1.0.4.dist-info/top_level.txt
wands_ce-1.0.4.dist-info/RECORD
