Metadata-Version: 2.1
Name: wands-ce
Version: 1.0.4
Summary: UNKNOWN
Home-page: https://github.com/onefeng/wands
Author: onefeng
Author-email: 15198086902@163.com
License: MIT
Platform: UNKNOWN
Classifier: License :: OSI Approved :: MIT License
Classifier: Programming Language :: Python
Classifier: Programming Language :: Python :: 3
Classifier: Programming Language :: Python :: 3.6
Classifier: Programming Language :: Python :: Implementation :: CPython
Classifier: Programming Language :: Python :: Implementation :: PyPy
Requires-Python: >=3
License-File: LICENSE
Requires-Dist: Flask (==2.0.3)
Requires-Dist: flask-script (==2.0.3)
